okboomer/__init__.py
okboomer-0.0.6.dist-info/LICENCE
okboomer-0.0.6.dist-info/METADATA
okboomer-0.0.6.dist-info/WHEEL
okboomer-0.0.6.dist-info/top_level.txt
okboomer-0.0.6.dist-info/RECORD
