Metadata-Version: 2.1
Name: okboomer
Version: 0.0.6
Summary: ok boomer
Home-page: UNKNOWN
Author: mat
Author-email: pypi@matdoes.dev
License: UNKNOWN
Platform: UNKNOWN
Classifier: Programming Language :: Python :: 3
Classifier: License :: OSI Approved :: MIT License
Classifier: Operating System :: OS Independent
Classifier: Framework :: AsyncIO
